shutterstock/__init__.py
shutterstock/__version__.py
shutterstock/ai_audio.py
shutterstock/audio.py
shutterstock/bulk_search.py
shutterstock/catalog.py
shutterstock/cli.py
shutterstock/contributors.py
shutterstock/cv.py
shutterstock/editorial.py
shutterstock/images.py
shutterstock/sfx.py
shutterstock/test.py
shutterstock/user.py
shutterstock/videos.py
shutterstock/utils/__init__.py
shutterstock/utils/prettyprint.py
shutterstock/utils/request.py
shutterstock/utils/request_helper.py
shutterstock_cli-1.1.38.dist-info/LICENSE.md
shutterstock_cli-1.1.38.dist-info/METADATA
shutterstock_cli-1.1.38.dist-info/WHEEL
shutterstock_cli-1.1.38.dist-info/entry_points.txt
shutterstock_cli-1.1.38.dist-info/top_level.txt
shutterstock_cli-1.1.38.dist-info/RECORD
