Metadata-Version: 2.1
Name: shutterstock-cli
Version: 1.1.38
Summary: A command-line utility that allows you to interact with the Shutterstock public API.
Home-page: https://github.com/shutterstock/shutterstock-cli
Author: Shutterstock
Author-email: tech.api.team@shutterstock.com
License: UNKNOWN
Keywords: shutterstock,api,images,videos,audio
Platform: UNKNOWN
Classifier: Development Status :: 5 - Production/Stable
Classifier: Environment :: Console
Classifier: Intended Audience :: Developers
Classifier: Intended Audience :: End Users/Desktop
Classifier: Operating System :: OS Independent
Classifier: License :: OSI Approved :: MIT License
Classifier: Programming Language :: Python
Classifier: Programming Language :: Python :: 3.8
Classifier: Programming Language :: Python :: 3.9
License-File: LICENSE.md
Requires-Dist: requests
Requires-Dist: click
Requires-Dist: pygments
